README.md
setup.py
xlyy_toolkit/__init__.py
xlyy_toolkit.egg-info/PKG-INFO
xlyy_toolkit.egg-info/SOURCES.txt
xlyy_toolkit.egg-info/dependency_links.txt
xlyy_toolkit.egg-info/top_level.txt
xlyy_toolkit/common/__init__.py
xlyy_toolkit/common/container_utils.py
xlyy_toolkit/common/file_utils.py
xlyy_toolkit/common/out_utils.py
xlyy_toolkit/common/str_utils.py
xlyy_toolkit/common/test.py
xlyy_toolkit/mysql/__init__.py
xlyy_toolkit/mysql/connect_utils.py
xlyy_toolkit/pyqt6/__init__.py
xlyy_toolkit/pyqt6/w_utils.py