Metadata-Version: 2.1
Name: xlyy-toolkit
Version: 1.0.2
Summary: xlyy's toolkit
Home-page: UNKNOWN
Author: NatsuriTsukine
Author-email: 398339897@qq.com
License: UNKNOWN
Platform: UNKNOWN
